[
  {
    "hash": "0eaa291b1acb98a2",
    "id": "0eaa291b1acb98a2",
    "question_preview": "Explain the concept of natural selection in evolut..."
  },
  {
    "hash": "1080f8a5f1ee1112",
    "id": "1080f8a5f1ee1112",
    "question_preview": "Describe the structure and function of mitochondri..."
  },
  {
    "id": "generated_1754462480471_0gfy5vivl",
    "question_preview": "Describe the process of photosynthesis and its imp..."
  },
  {
    "id": "generated_1754462480471_4qz3i88gd",
    "question_preview": "What is the main function of mitochondria in a cel..."
  },
  {
    "id": "generated_1754462480471_bojymikdo",
    "question_preview": "Which blood type is considered the universal donor..."
  },
  {
    "id": "generated_1754462480471_qeselodoz",
    "question_preview": "Explain the process of photosynthesis in plants...."
  },
  {
    "id": "generated_1754462480471_vbsug88ld",
    "question_preview": "What are the four stages of mitosis?..."
  },
  {
    "id": "generated_1754462480472_0xhvsa0s0",
    "question_preview": "Explain the process of photosynthesis in plants...."
  },
  {
    "id": "generated_1754462480472_2lax2elva",
    "question_preview": "Explain the process of photosynthesis in plants...."
  },
  {
    "id": "generated_1754462480472_9bbm2420w",
    "question_preview": "Explain the process of photosynthesis in plants...."
  },
  {
    "id": "generated_1754462480472_z0bzdqlk5",
    "question_preview": "Explain the process of photosynthesis in plants...."
  }
]