{
  "id": "history_sastera_sains_sosial_001",
  "type": "multiple_choice",
  "question": "When did Malaysia gain independence?",
  "options": ["31st August 1957", "16th September 1963", "13th May 1969", "1st January 1960"],
  "answer": "31st August 1957",
  "explanation": {
    "en": "Malaysia (then Malaya) gained independence from British colonial rule on 31st August 1957, with Tunku Abdul Rahman as the first Prime Minister.",
    "bm": "Malaysia (ketika itu Malaya) memperoleh kemerdekaan daripada pemerintahan kolonial British pada 31 Ogos 1957, dengan Tunku Abdul Rahman sebagai Perdana Menteri pertama."
  },
  "hint": {
    "en": "Think about Merdeka Day celebration date",
    "bm": "Fikirkan tentang tarikh perayaan Hari Merdeka"
  },
  "difficulty": "easy",
  "xp_value": 10,
  "subject": "history",
  "program": "sastera_sains_sosial",
  "topic": "malaysian_history",
  "subtopic": "independence",
  "metadata": {
    "created_date": "2025-08-03",
    "level": "form_4",
    "curriculum": "mrsm"
  }
}